{"otherData": {},"traceEvents":[{},{"cat":"function","dur":1,"name":"void __cdecl Renderer::Shutdown(void)","ph":"X","pid":0,"tid":16880,"ts":970701592602.800},{"cat":"function","dur":100,"name":"__cdecl Application::~Application(void)","ph":"X","pid":0,"tid":16880,"ts":970701592602.800},{"cat":"function","dur":81552,"name":"void __cdecl WindowsWindow::Shutdown(void)","ph":"X","pid":0,"tid":16880,"ts":970701592759.200},{"cat":"function","dur":81669,"name":"__cdecl WindowsWindow::~WindowsWindow(void)","ph":"X","pid":0,"tid":16880,"ts":970701592759.100}]}